pyscreeningfs/__init__.py
pyscreeningfs/fsonline.cp310-win_amd64.pyd
pyscreeningfs/online_screening.py
pyscreeningfs-0.1.1.dist-info/licenses/LICENSE
pyscreeningfs-0.1.1.dist-info/METADATA
pyscreeningfs-0.1.1.dist-info/WHEEL
pyscreeningfs-0.1.1.dist-info/top_level.txt
pyscreeningfs-0.1.1.dist-info/RECORD
