Metadata-Version: 2.4
Name: pyscreeningfs
Version: 0.1.1
Summary: This is a Python implementation by the authors of the paper 'Online Feature Screening for Data Streams With Concept Drift' from Dr. Mingyuan Wang and Dr. Adrian Barbu. Contain various feature selection methods.
Home-page: https://github.com/tbonewmy/Online-Feature-Screening-for-Datastream-with-Sparsity-Concept-Drifting
Author: Mingyuan Wang
Author-email: bruce.wmy.research@gmail.com
License: Apache-2.0
Keywords: feature selection,feature screening,variable screening,online learning,online feature selection,concept drift,data drift,machine learning,artificial intelligence,statistics
Classifier: Programming Language :: Python :: 3
Classifier: Programming Language :: Python :: 3.10
Classifier: Operating System :: Microsoft :: Windows
Classifier: Development Status :: 3 - Alpha
Classifier: Intended Audience :: Science/Research
Classifier: Topic :: Scientific/Engineering
Classifier: Topic :: Scientific/Engineering :: Artificial Intelligence
Classifier: Topic :: Scientific/Engineering :: Bio-Informatics
Classifier: Topic :: Scientific/Engineering :: Information Analysis
Requires-Python: >=3.10
License-File: LICENSE
Requires-Dist: numpy>=2.2.4
Dynamic: author
Dynamic: author-email
Dynamic: classifier
Dynamic: description
Dynamic: description-content-type
Dynamic: home-page
Dynamic: keywords
Dynamic: license
Dynamic: license-file
Dynamic: requires-dist
Dynamic: requires-python
Dynamic: summary
